wetransfer/__init__.py
wetransfer/base.py
wetransfer/board.py
wetransfer/exc.py
wetransfer/file.py
wetransfer/http.py
wetransfer/transfer.py
wetransfer/tests/__init__.py
wetransfer/tests/test_authorization.py
wetransfer/tests/test_board.py
wetransfer/tests/test_transfer.py
py3wetransfer-1.0.3.dist-info/LICENSE
py3wetransfer-1.0.3.dist-info/METADATA
py3wetransfer-1.0.3.dist-info/WHEEL
py3wetransfer-1.0.3.dist-info/top_level.txt
py3wetransfer-1.0.3.dist-info/RECORD
