Metadata-Version: 2.1
Name: py3wetransfer
Version: 1.0.3
Summary: A Python 3 wrapper to use WeTransfer API V2 transfer and board
Home-page: https://github.com/fliot/py3wetransfer
Author: Francois Liot
Author-email: francois@liot.org
Maintainer: Sander Huijsen
Maintainer-email: sander.huijsen@gmail.com
License: UNKNOWN
Platform: UNKNOWN
Classifier: Development Status :: 5 - Production/Stable
Classifier: Intended Audience :: Developers
Classifier: License :: OSI Approved :: Apache Software License
Classifier: Programming Language :: Python :: 3
Classifier: Operating System :: OS Independent
Classifier: Topic :: Software Development :: Libraries :: Python Modules
Classifier: Topic :: Internet :: WWW/HTTP
Requires-Dist: requests (>=2.7.0)
